kalyke/__init__.py
kalyke/_version.py
kalyke/_version.pyi
kalyke/exceptions.py
kalyke/py.typed
kalyke/clients/__init__.py
kalyke/clients/apns.py
kalyke/clients/live_activity.py
kalyke/clients/voip.py
kalyke/models/__init__.py
kalyke/models/apns_config.py
kalyke/models/apns_priority.py
kalyke/models/apns_push_type.py
kalyke/models/critical_sound.py
kalyke/models/interruption_level.py
kalyke/models/live_activity_event.py
kalyke/models/payload.py
kalyke/models/payload_alert.py
kalyke_apns-1.2.0.dist-info/METADATA
kalyke_apns-1.2.0.dist-info/WHEEL
kalyke_apns-1.2.0.dist-info/licenses/LICENSE
kalyke_apns-1.2.0.dist-info/RECORD
