Metadata-Version: 2.4
Name: kalyke-apns
Version: 1.2.0
Summary: A library for interacting with APNs and VoIP using HTTP/2.
Project-URL: Source, https://github.com/nnsnodnb/kalyke
Author-email: nnsnodnb <nnsnodnb@gmail.com>
License-Expression: MIT
License-File: LICENSE
Keywords: apns,apns provider api,apple push notifications,liveactivity,voip
Classifier: Development Status :: 5 - Production/Stable
Classifier: Intended Audience :: Developers
Classifier: License :: OSI Approved :: MIT License
Classifier: Operating System :: OS Independent
Classifier: Programming Language :: Python :: 3
Classifier: Programming Language :: Python :: 3.10
Classifier: Programming Language :: Python :: 3.11
Classifier: Programming Language :: Python :: 3.12
Classifier: Programming Language :: Python :: 3.13
Classifier: Programming Language :: Python :: 3.14
Classifier: Topic :: Communications
Classifier: Topic :: Internet
Classifier: Topic :: Software Development :: Libraries
Requires-Python: <3.15,>=3.10.0
Requires-Dist: httpx[http2]<0.29.0,>=0.23.0
Requires-Dist: pyjwt[crypto]<2.11.0,>=2.0.0
